langchain_chroma-1.0.0a1.dist-info/METADATA
langchain_chroma-1.0.0a1.dist-info/WHEEL
langchain_chroma-1.0.0a1.dist-info/entry_points.txt
langchain_chroma-1.0.0a1.dist-info/licenses/LICENSE
langchain_chroma/__init__.py
langchain_chroma/py.typed
langchain_chroma/vectorstores.py
langchain_chroma-1.0.0a1.dist-info/RECORD
