Metadata-Version: 2.1
Name: langchain-chroma
Version: 1.0.0a1
Summary: An integration package connecting Chroma and LangChain.
License: MIT
Project-URL: Source Code, https://github.com/langchain-ai/langchain/tree/master/libs/partners/chroma
Project-URL: Release Notes, https://github.com/langchain-ai/langchain/releases?q=tag%3A%22langchain-chroma%3D%3D0%22&expanded=true
Project-URL: repository, https://github.com/langchain-ai/langchain
Requires-Python: <4.0.0,>=3.10.0
Requires-Dist: langchain-core<2.0.0,>=1.0.0a6
Requires-Dist: numpy>=1.26.0; python_version < "3.13"
Requires-Dist: numpy>=2.1.0; python_version >= "3.13"
Requires-Dist: chromadb<2.0.0,>=1.0.20
